isotools/__init__.py
isotools/_gene_plots.py
isotools/_transcriptome_filter.py
isotools/_transcriptome_io.py
isotools/_transcriptome_stats.py
isotools/_utils.py
isotools/decorators.py
isotools/domains.py
isotools/gene.py
isotools/plots.py
isotools/run_isotools.py
isotools/short_read.py
isotools/splice_graph.py
isotools/transcriptome.py
isotools-2.0.0.dist-info/licenses/LICENSE.txt
isotools-2.0.0.dist-info/METADATA
isotools-2.0.0.dist-info/WHEEL
isotools-2.0.0.dist-info/top_level.txt
isotools-2.0.0.dist-info/RECORD
