Metadata-Version: 2.4
Name: isotools
Version: 2.0.0
Summary: Framework for the analysis of long read transcriptome sequencing data
Home-page: https://github.com/HerwigLab/IsoTools2
Author: Matthias Lienhard, Yalan Bi
Author-email: Matthias Lienhard <lienhard@molgen.mpg.de>, Yalan Bi <yalan_bi@molgen.mpg.de>
License-Expression: MIT
Project-URL: Homepage, https://github.com/HerwigLab/IsoTools2
Project-URL: Documentation, https://isotools.readthedocs.io/
Project-URL: Repository, https://github.com/HerwigLab/IsoTools2.git
Project-URL: Issues, https://github.com/HerwigLab/IsoTools2/issues
Project-URL: Changelog, https://github.com/HerwigLab/IsoTools2/blob/master/CHANGELOG.md
Classifier: Programming Language :: Python :: 3
Classifier: Operating System :: MacOS
Classifier: Operating System :: POSIX :: Linux
Requires-Python: >=3.10
License-File: LICENSE.txt
Requires-Dist: numpy
Requires-Dist: pandas
Requires-Dist: tqdm
Requires-Dist: intervaltree
Requires-Dist: matplotlib
Requires-Dist: seaborn
Requires-Dist: biopython
Requires-Dist: pysam
Requires-Dist: umap-learn
Requires-Dist: scikit-learn
Requires-Dist: scipy
Requires-Dist: statsmodels
Requires-Dist: pyhmmer
Requires-Dist: requests
Requires-Dist: CPAT
Requires-Dist: python-ternary
Dynamic: license-file
